pypomes_cloud/__init__.py
pypomes_cloud/azure_pomes.py
pypomes_cloud-0.1.8.dist-info/METADATA
pypomes_cloud-0.1.8.dist-info/WHEEL
pypomes_cloud-0.1.8.dist-info/licenses/LICENSE
pypomes_cloud-0.1.8.dist-info/RECORD
